my_ghost_writer/__init__.py
my_ghost_writer/__version__.py
my_ghost_writer/app.py
my_ghost_writer/constants.py
my_ghost_writer/middlewares.py
my_ghost_writer/session_logger.py
my_ghost_writer/text_parsers.py
my_ghost_writer/type_hints.py
my_ghost_writer-0.3.0.dist-info/LICENSE
my_ghost_writer-0.3.0.dist-info/METADATA
my_ghost_writer-0.3.0.dist-info/WHEEL
my_ghost_writer-0.3.0.dist-info/RECORD
