Metadata-Version: 2.3
Name: my-ghost-writer
Version: 0.3.0
Summary: A simple help for writers
License: AGPL-3.0
Author: alessandro trinca tornidor
Author-email: alessandro@trinca.tornidor.com
Requires-Python: >=3.10,<4.0.0
Classifier: License :: OSI Approved :: GNU Affero General Public License v3
Classifier: Programming Language :: Python :: 3
Classifier: Programming Language :: Python :: 3.10
Classifier: Programming Language :: Python :: 3.11
Classifier: Programming Language :: Python :: 3.12
Classifier: Programming Language :: Python :: 3.13
Requires-Dist: nltk (>=3.9.1,<4.0.0)
Requires-Dist: python-dotenv (>=1.1.0,<2.0.0)
Requires-Dist: structlog (>=25.2.0,<26.0.0)
